Workbook

Sheet Main
A1: Product No. | B1: Brand/ Name | C1: Units | D1: Cost | E1: Cost per unit | F1: Unit Sold | G1: Revenue | H1: Merchant pay | I1: Merchant discount | J1: Price per unit | K1: Profit | L1: ROI | M1: Inventory
A2: 1 | B2: AlpK2 Jap | C2: ='BP Machine'!C4 -> 37 | D2: ='BP Machine'!F4 -> 69036.316 | E2: =D2/C2 -> 1865.8464 | F2: ='BP Machine'!I4 | G2: ='BP Machine'!H4 | H2: =#REF! -> #REF! | I2: =#REF! -> #REF! | J2: =G2/F2 -> #DIV/0! | K2: =(J2-E2)*F2 -> #DIV/0! | L2: =K2/D2 -> #DIV/0! | M2: =C2-F2 -> 37 | O2: =M2*E2 -> 69036.316
A3: 2 | B3: BSMI Heavy | C3: =Stethoscope!$C$4 -> 27 | D3: =Stethoscope!$F$4 -> 54794.545 | E3: =D3/C3 -> 2029.4276 | F3: =Stethoscope!$H$4 | G3: =#REF! -> #REF! | H3: =#REF! -> #REF! | I3: =#REF! -> #REF! | J3: =G3/F3 -> #REF! | K3: =(J3-E3)*F3 -> #REF! | L3: =K3/D3 -> #REF! | M3: =C3-F3 -> 27 | O3: =M3*E3 -> 54794.545
A4: 3 | B4: Instrument | C4: =Instrument!C12 | D4: =Instrument!G12 | E4: =D4/C4 -> #DIV/0! | F4: =Instrument!J12 | G4: =Instrument!I12 | H4: =Instrument!M12 | I4: =Instrument!N12 | J4: =G4/F4 -> #DIV/0! | K4: =(J4-E4)*F4 -> #DIV/0! | L4: =K4/D4 -> #DIV/0! | M4: =C4-F4 -> 0 | O4: =M4*E4 -> #DIV/0!
A5: 4 | B5: OT Dress | C5: ='OT Dress'!D25 | D5: ='OT Dress'!G25 | E5: =D5/C5 -> #DIV/0! | F5: ='OT Dress'!J25 | G5: ='OT Dress'!I25 | H5: ='OT Dress'!M25 | I5: ='OT Dress'!N25 | J5: =G5/F5 -> #DIV/0! | K5: =(J5-E5)*F5 -> #DIV/0! | L5: =K5/D5 -> #DIV/0! | M5: =C5-F5 -> 0 | O5: =M5*E5 -> #DIV/0!

Sheet Shareholders info
A1: Date | B1: Name | C1: Contact | D1: Investment | E1: Tenure | F1: Profit share | G1: Profit | H1: Paid Back | I1: Remaining
B2: Opi | D2: 18580 | H2: 4749.7191 | I2: =D2+G2-H2 -> 13830.281
B3: Tasnim | D3: 15000 | I3: =D3+G3-H3 -> 15000
B4: Remon | D4: 18000 | H4: =18000+4500 -> 22500
B5: Hamim | D5: 8800 | H5: =8700+2230 -> 10930

Sheet BP Machine
A1: BP MACHINE
A3: Product no. | B3: Brand | C3: Units | D3: Cost=/ | E3: Transport Cost | F3: Final Cost | G3: Cost per unit | H3: Revenue=/ | I3: Unit Sold | J3: Price per unit | K3: Profit | L3: Inventory
A4: 1 | B4: AlpK2 Jap | C4: 37 | D4: 68435 | E4: 601.31579 | F4: =D4+E4+O4 -> 69036.316 | G4: =iferror(F4/C4,0) -> 1865.8464 | J4: =iferror(H4/I4,0) -> 0
A5: 2 | B5: Bp Cuff | C5: 2 | D5: 1200 | E5: 10.526316 | F5: =D5+E5 -> 1210.5263 | G5: =iferror(F5/C5,0) -> 605.26316 | J5: =iferror(H5/I5,0) -> 0 | K5: =(J5-G5)*I5 -> 0 | L5: =C5-I5 -> 2

Sheet Stethoscope
A1: STETHOSCOPE
A3: Product no. | B3: Brand | C3: Units | D3: Cost=/ | E3: Transport/= | F3: Final Cost | G3: Cost per unit | H3: Unit Sold | I3: In stock | J3: Column 1
A4: 1 | B4: BSMI heavy | C4: 27 | D4: 54000 | E4: 794.54545 | F4: =Table2[Cost=/]+Table2[Transport/=] -> 54794.545 | G4: =iferror(Table2[Final Cost]/Table2[Units],0) -> 2029.4276 | I4: =Table2[Units]-Table2[Unit Sold] -> 27

Sheet Instrument
A1: INSTRUMENT
A3: Product no. | B3: Name | C3: Units | D3: Error check | E3: Cost=/ | F3: Transport/= | G3: Final Cost | H3: Cost per unit | I3: Revenue=/ | J3: Unit Sold | K3: Price per unit | L3: Profit | M3: Merchant Pay | N3: Merchant Discount | O3: ROI | P3: Inventory
A4: 1 | B4: Hammer | C4: 70 | D4: =MMC!E5+CuMC!E6+CuMC!E45+CuMC!E83 -> #REF! | E4: 7150 | F4: 167.7908 | G4: =E4+F4 -> 7317.7908 | H4: =iferror(G4/C4,0) -> 104.53987 | I4: =MMC!L5+CuMC!L45+CuMC!L83+CuMC!L6 -> #REF! | J4: =MMC!H5+CuMC!H6+CuMC!H45+CuMC!H83 -> #REF! | K4: =iferror(I4/J4,0) -> 0 | L4: =(K4-H4)*J4 -> #REF! | O4: =iferror(L4*100/G4,0) -> 0 | P4: =C4-J4 -> #REF!
A5: 2 | B5: Thermometer(Toshiba) | C5: 71 | D5: =MMC!E6+CuMC!E7+CuMC!E46+CuMC!E84 -> #REF! | E5: 5675 | F5: 178.08492 | G5: =E5+F5 -> 5853.0849 | H5: =iferror(G5/C5,0) -> 82.437816 | I5: =MMC!L6+CuMC!L46+CuMC!L84+CuMC!L7 -> #REF! | J5: =MMC!H6+CuMC!H7+CuMC!H46+CuMC!H84 -> #REF! | K5: =iferror(I5/J5,0) -> 0 | L5: =(K5-H5)*J5 -> #REF! | O5: =iferror(L5*100/G5,0) -> 0 | P5: =C5-J5 -> #REF!
A6: 3 | B6: Tuning Fork(256) | C6: 70 | D6: =MMC!E7+CuMC!E8+CuMC!E47+CuMC!E85 -> #REF! | E6: 4900 | F6: 167.7908 | G6: =E6+F6 -> 5067.7908 | H6: =iferror(G6/C6,0) -> 72.397011 | I6: =MMC!L7+CuMC!L47+CuMC!L85+CuMC!L8 -> #REF! | J6: =MMC!H7+CuMC!H8+CuMC!H47+CuMC!H85 -> #REF! | K6: =iferror(I6/J6,0) -> 0 | L6: =(K6-H6)*J6 -> #REF! | O6: =iferror(L6*100/G6,0) -> 0 | P6: =C6-J6 -> #REF!
A7: 4 | B7: Tongue depressor | C7: 70 | D7: =MMC!E8+CuMC!E9+CuMC!E48+CuMC!E86 -> #REF! | E7: 2100 | F7: 167.7908 | G7: =E7+F7 -> 2267.7908 | H7: =iferror(G7/C7,0) -> 32.397011 | I7: =MMC!L8+CuMC!L48+CuMC!L86+CuMC!L9 -> #REF! | J7: =MMC!H8+CuMC!H9+CuMC!H48+CuMC!H86 -> #REF! | K7: =iferror(I7/J7,0) -> 0 | L7: =(K7-H7)*J7 -> #REF! | O7: =iferror(L7*100/G7,0) -> 0 | P7: =C7-J7 -> #REF!
A8: 5 | B8: Pen Torch | C8: 70 | D8: =MMC!E9+CuMC!E10+CuMC!E49+CuMC!E87 -> #REF! | E8: 9450 | F8: 167.7908 | G8: =E8+F8 -> 9617.7908 | H8: =iferror(G8/C8,0) -> 137.39701 | I8: =MMC!L9+CuMC!L49+CuMC!L87+CuMC!L10 -> #REF! | J8: =MMC!H9+CuMC!H10+CuMC!H49+CuMC!H87 -> #REF! | K8: =iferror(I8/J8,0) -> 0 | L8: =(K8-H8)*J8 -> #REF! | O8: =iferror(L8*100/G8,0) -> 0 | P8: =C8-J8 -> #REF!
A9: 6 | B9: Cotton | C9: 70 | D9: =MMC!E10+CuMC!E11+CuMC!E50+CuMC!E88 -> #REF! | E9: 700 | F9: 167.7908 | G9: =E9+F9 -> 867.7908 | H9: =iferror(G9/C9,0) -> 12.397011 | I9: =MMC!L10+CuMC!L50+CuMC!L88+CuMC!L11 -> #REF! | J9: =MMC!H10+CuMC!H11+CuMC!H50+CuMC!H88 -> #REF! | K9: =iferror(I9/J9,0) -> 0 | L9: =(K9-H9)*J9 -> #REF! | O9: =iferror(L9*100/G9,0) -> 0 | P9: =C9-J9 -> #REF!
A10: 7 | B10: Measuring Tape | C10: 70 | D10: =MMC!E11+CuMC!E12+CuMC!E51+CuMC!E89 -> #REF! | E10: 1400 | F10: 167.7908 | G10: =E10+F10 -> 1567.7908 | H10: =iferror(G10/C10,0) -> 22.397011 | I10: =MMC!L11+CuMC!L51+CuMC!L89+CuMC!L12 -> #REF! | J10: =MMC!H11+CuMC!H12+CuMC!H51+CuMC!H89 -> #REF! | K10: =iferror(I10/J10,0) -> 0 | L10: =(K10-H10)*J10 -> #REF! | O10: =iferror(L10*100/G10,0) -> 0 | P10: =C10-J10 -> #REF!
A11: 8 | B11: Bag | C11: 68 | D11: =MMC!E12+CuMC!E13+CuMC!E52+CuMC!E90 -> #REF! | E11: 1115 | G11: =E11+F11 -> 1115 | H11: =iferror(G11/C11,0) -> 16.397059 | I11: =MMC!L12+CuMC!L52+CuMC!L90+CuMC!L13 -> #REF! | J11: =MMC!H12+CuMC!H13+CuMC!H52+CuMC!H90 -> #REF! | K11: =iferror(I11/J11,0) -> 0 | L11: =(K11-H11)*J11 -> #REF! | O11: =iferror(L11*100/G11,0) -> 0 | P11: =C11-J11 -> #REF!

Sheet OT Dress
A1: OT DRESS
A3: Product no. | B3: Colour | C3: Size | D3: Units | E3: Cost=/ | F3: Transport/= | G3: Final Cost | H3: Cost per unit | I3: Revenue=/ | J3: Unit Sold | K3: Price per unit | L3: Profit | M3: Merchant pay | N3: Merchant Discount | O3: ROI | P3: Inventory
A4: 1 | B4: Navy | C4: 34 | D4: 3 | E4: 1645.1681 | F4: 35.607233 | G4: =E4+F4 -> 1680.7753 | H4: =iferror(G4/D4,0) -> 560.25843 | I4: =MMC!L14+CuMC!L92+CuMC!L54+CuMC!L15 -> #REF! | J4: =MMC!H14+CuMC!H15+CuMC!H54+CuMC!H92 -> #REF! | K4: =iferror(I4/J4,0) -> 0 | L4: =(K4-H4)*J4 -> #REF! | O4: =iferror(L4*100/G4,0) -> 0 | P4: =D4-J4 -> #REF!
B5: Navy | C5: 36 | D5: 7 | E5: 3840.3571 | F5: 54.762876 | G5: =E5+F5 -> 3895.12 | H5: =iferror(G5/D5,0) -> 556.44572 | I5: =MMC!L15+CuMC!L93+CuMC!L55+CuMC!L16 -> #REF! | J5: =MMC!H15+CuMC!H16+CuMC!H55+CuMC!H93 -> #REF! | K5: =iferror(I5/J5,0) -> 0 | L5: =(K5-H5)*J5 -> #REF! | O5: =iferror(L5*100/G5,0) -> 0 | P5: =D5-J5 -> #REF!
B6: Navy | C6: 38 | D6: 25 | E6: 13850.431 | F6: 396.52758 | G6: =E6+F6 -> 14246.958 | H6: =iferror(G6/D6,0) -> 569.87833 | I6: =MMC!L16+CuMC!L94+CuMC!L56+CuMC!L17 -> #REF! | J6: =MMC!H16+CuMC!H17+CuMC!H56+CuMC!H94 -> #REF! | K6: =iferror(I6/J6,0) -> 0 | L6: =(K6-H6)*J6 -> #REF! | O6: =iferror(L6*100/G6,0) -> 0 | P6: =D6-J6 -> #REF!
B7: Navy | C7: 40 | D7: 20 | E7: 11092.983 | F7: 298.86153 | G7: =E7+F7 -> 11391.845 | H7: =iferror(G7/D7,0) -> 569.59224 | I7: =MMC!L17+CuMC!L95+CuMC!L57+CuMC!L18 -> #REF! | J7: =MMC!H17+CuMC!H18+CuMC!H57+CuMC!H95 -> #REF! | K7: =iferror(I7/J7,0) -> 0 | L7: =(K7-H7)*J7 -> #REF! | O7: =iferror(L7*100/G7,0) -> 0 | P7: =D7-J7 -> #REF!
B8: Navy | C8: 42 | D8: 14 | E8: 7774.1071 | F8: 135.18304 | G8: =E8+F8 -> 7909.2902 | H8: =iferror(G8/D8,0) -> 564.9493 | I8: =MMC!L18+CuMC!L96+CuMC!L58+CuMC!L19 -> #REF! | J8: =MMC!H18+CuMC!H19+CuMC!H58+CuMC!H96 -> #REF! | K8: =iferror(I8/J8,0) -> 0 | L8: =(K8-H8)*J8 -> #REF! | O8: =iferror(L8*100/G8,0) -> 0 | P8: =D8-J8 -> #REF!
B9: Navy | C9: 44 | D9: 4 | E9: 2201.0714 | F9: 29.449761 | G9: =E9+F9 -> 2230.5212 | H9: =iferror(G9/D9,0) -> 557.6303 | I9: =MMC!L19+CuMC!L97+CuMC!L59+CuMC!L20 -> #REF! | J9: =MMC!H19+CuMC!H20+CuMC!H59+CuMC!H97 -> #REF! | K9: =iferror(I9/J9,0) -> 0 | L9: =(K9-H9)*J9 -> #REF! | O9: =iferror(L9*100/G9,0) -> 0 | P9: =D9-J9 -> #REF!
B10: Sky | C10: 34 | D10: 1 | E10: 539.28571 | F10: 4.7248804 | G10: =E10+F10 -> 544.01059 | H10: =iferror(G10/D10,0) -> 544.01059 | I10: =MMC!L21+CuMC!L99+CuMC!L61+CuMC!L22 -> #REF! | J10: =MMC!H21+CuMC!H22+CuMC!H61+CuMC!H99 -> #REF! | K10: =iferror(I10/J10,0) -> 0 | L10: =(K10-H10)*J10 -> #REF! | O10: =iferror(L10*100/G10,0) -> 0 | P10: =D10-J10 -> #REF!
B11: Sky | C11: 36 | D11: 2 | E11: 1095.1681 | F11: 25.313116 | G11: =E11+F11 -> 1120.4812 | H11: =iferror(G11/D11,0) -> 560.24059 | I11: =MMC!L22+CuMC!L100+CuMC!L62+CuMC!L23 -> #REF! | J11: =MMC!H22+CuMC!H23+CuMC!H62+CuMC!H100 -> #REF! | K11: =iferror(I11/J11,0) -> 0 | L11: =(K11-H11)*J11 -> #REF! | O11: =iferror(L11*100/G11,0) -> 0 | P11: =D11-J11 -> #REF!
B12: Sky | C12: 38 | D12: 7 | E12: 3847.8571 | F12: 60.89733 | G12: =E12+F12 -> 3908.7545 | H12: =iferror(G12/D12,0) -> 558.3935 | I12: =MMC!L23+CuMC!L101+CuMC!L63+CuMC!L24 -> #REF! | J12: =MMC!H23+CuMC!H24+CuMC!H63+CuMC!H101 -> #REF! | K12: =iferror(I12/J12,0) -> 0 | L12: =(K12-H12)*J12 -> #REF! | O12: =iferror(L12*100/G12,0) -> 0 | P12: =D12-J12 -> #REF!
B13: Sky | C13: 40 | D13: 7 | E13: 3847.8571 | F13: 60.89733 | G13: =E13+F13 -> 3908.7545 | H13: =iferror(G13/D13,0) -> 558.3935 | I13: =MMC!L24+CuMC!L102+CuMC!L64+CuMC!L25 -> #REF! | J13: =MMC!H24+CuMC!H25+CuMC!H64+CuMC!H102 -> #REF! | K13: =iferror(I13/J13,0) -> 0 | L13: =(K13-H13)*J13 -> #REF! | O13: =iferror(L13*100/G13,0) -> 0 | P13: =D13-J13 -> #REF!
B14: Sky | C14: 42 | D14: 4 | E14: 2219.2857 | F14: 41.153452 | G14: =E14+F14 -> 2260.4392 | H14: =iferror(G14/D14,0) -> 565.10979 | I14: =MMC!L25+CuMC!L103+CuMC!L65+CuMC!L26 -> #REF! | J14: =MMC!H25+CuMC!H26+CuMC!H65+CuMC!H103 -> #REF! | K14: =iferror(I14/J14,0) -> 0 | L14: =(K14-H14)*J14 -> #REF! | O14: =iferror(L14*100/G14,0) -> 0 | P14: =D14-J14 -> #REF!
B15: Green | C15: 34 | D15: 1 | E15: 539.28571 | F15: 4.7248804 | G15: =E15+F15 -> 544.01059 | H15: =iferror(G15/D15,0) -> 544.01059 | I15: =MMC!L28+CuMC!L106+CuMC!L68+CuMC!L29 -> #REF! | J15: =MMC!H28+CuMC!H29+CuMC!H68+CuMC!H106 -> #REF! | K15: =iferror(I15/J15,0) -> 0 | L15: =(K15-H15)*J15 -> #REF! | O15: =iferror(L15*100/G15,0) -> 0 | P15: =D15-J15 -> #REF!
B16: Green | C16: 36 | D16: 1 | E16: 539.28571 | F16: 4.7248804 | G16: =E16+F16 -> 544.01059 | H16: =iferror(G16/D16,0) -> 544.01059 | I16: =MMC!L29+CuMC!L107+CuMC!L69+CuMC!L30 -> #REF! | J16: =MMC!H29+CuMC!H30+CuMC!H69+CuMC!H107 -> #REF! | K16: =iferror(I16/J16,0) -> 0 | L16: =(K16-H16)*J16 -> #REF! | O16: =iferror(L16*100/G16,0) -> 0 | P16: =D16-J16 -> #REF!
B17: Green | C17: 38 | D17: 3 | E17: 1628.5714 | F17: 19.743878 | G17: =E17+F17 -> 1648.3153 | H17: =iferror(G17/D17,0) -> 549.43844 | I17: =MMC!L30+CuMC!L108+CuMC!L70+CuMC!L31 -> #REF! | J17: =MMC!H30+CuMC!H31+CuMC!H70+CuMC!H108 -> #REF! | K17: =iferror(I17/J17,0) -> 0 | L17: =(K17-H17)*J17 -> #REF! | O17: =iferror(L17*100/G17,0) -> 0 | P17: =D17-J17 -> #REF!
B18: Green | C18: 40 | D18: 1 | E18: 550 | F18: 10.294118 | G18: =E18+F18 -> 560.29412 | H18: =iferror(G18/D18,0) -> 560.29412 | I18: =MMC!L31+CuMC!L109+CuMC!L71+CuMC!L32 -> #REF! | J18: =MMC!H31+CuMC!H32+CuMC!H71+CuMC!H109 -> #REF! | K18: =iferror(I18/J18,0) -> 0 | L18: =(K18-H18)*J18 -> #REF! | O18: =iferror(L18*100/G18,0) -> 0 | P18: =D18-J18 -> #REF!
B19: Green | C19: 42 | D19: 1 | E19: 539.28571 | F19: 4.7248804 | G19: =E19+F19 -> 544.01059 | H19: =iferror(G19/D19,0) -> 544.01059 | I19: =MMC!L32+CuMC!L110+CuMC!L72+CuMC!L33 -> #REF! | J19: =MMC!H32+CuMC!H33+CuMC!H72+CuMC!H110 -> #REF! | K19: =iferror(I19/J19,0) -> 0 | L19: =(K19-H19)*J19 -> #REF! | O19: =iferror(L19*100/G19,0) -> 0 | P19: =D19-J19 -> #REF!

Sheet Books
A1: BOOKS
A3: Product no. | B3: Brand | C3: Units | D3: Cost=/ | E3: Transport/= | F3: Final Cost | G3: Cost per unit | H3: Revenue=/ | I3: Unit Sold | J3: Price per unit | K3: Profit | L3: ROI
A4: 1 | B4: IMCI | C4: 21 | D4: =21*120 -> 2520 | E4: 270.6015 | F4: =D4+E4 -> 2790.6015 | G4: =F4/C4 -> 132.88579 | H4: 4080 | I4: 21 | J4: =H4/I4 -> 194.28571 | K4: =(J4-G4)*I4 -> 1289.3985 | L4: =K4*100/F4 -> 46.205038
A5: 2 | B5: Macleod | C5: 1 | D5: 200 | E5: 5.2631579 | F5: =D5+E5 -> 205.26316 | G5: =F5/C5 -> 205.26316 | H5: 200 | I5: 1 | J5: =H5/I5 -> 200 | K5: =(J5-G5)*I5 -> -5.2631579 | L5: =K5*100/F5 -> -2.5641026
A6: 3 | B6: Lange Micro | C6: 1 | D6: 400 | E6: 5.2631579 | F6: =D6+E6 -> 405.26316 | G6: =F6/C6 -> 405.26316 | H6: 400 | I6: 1 | J6: =H6/I6 -> 400 | K6: =(J6-G6)*I6 -> -5.2631579 | L6: =K6*100/F6 -> -1.2987013
A7: 4 | B7: Matrix QB | C7: 1 | D7: 280 | E7: 10.714286 | F7: =D7+E7 -> 290.71429 | G7: =F7/C7 -> 290.71429 | H7: 100 | I7: 1 | J7: =H7/I7 -> 100 | K7: =(J7-G7)*I7 -> -190.71429 | L7: =K7*100/F7 -> -65.601966
A8: 5 | B8: Abdullah Short case | C8: 2 | D8: 840 | E8: 10.526316 | F8: =D8+E8 -> 850.52632 | G8: =F8/C8 -> 425.26316 | H8: 840 | I8: 2 | J8: =H8/I8 -> 420 | K8: =(J8-G8)*I8 -> -10.526316 | L8: =K8*100/F8 -> -1.2376238
A9: 6 | B9: Arif Anatomy | C9: 5 | D9: 8100 | E9: 177.77778 | F9: =D9+E9 -> 8277.7778 | G9: =F9/C9 -> 1655.5556 | H9: 7190 | I9: 5 | J9: =H9/I9 -> 1438 | K9: =(J9-G9)*I9 -> -1087.7778 | L9: =K9*100/F9 -> -13.14094
A10: 7 | B10: Clonus | C10: 4 | D10: 2060 | E10: 151.11111 | F10: =D10+E10 -> 2211.1111 | G10: =F10/C10 -> 552.77778 | H10: 1740 | I10: 3 | J10: =H10/I10 -> 580 | K10: =(J10-G10)*I10 -> 81.666667 | L10: =K10*100/F10 -> 3.6934673
A11: 8 | B11: Endeavour med+surg | C11: 2 | D11: 1200 | E11: 71.111111 | F11: =D11+E11 -> 1271.1111 | G11: =F11/C11 -> 635.55556 | H11: 1300 | I11: 2 | J11: =H11/I11 -> 650 | K11: =(J11-G11)*I11 -> 28.888889 | L11: =K11*100/F11 -> 2.2727273
A12: 9 | B12: Arif Physio | C12: 1 | D12: 1230 | E12: 45 | F12: =D12+E12 -> 1275 | G12: =F12/C12 -> 1275 | H12: 1300 | I12: 1 | J12: =H12/I12 -> 1300 | K12: =(J12-G12)*I12 -> 25 | L12: =K12*100/F12 -> 1.9607843
A13: 10 | B13: Arif Biochem | C13: 3 | D13: 3660 | E13: 230 | F13: =D13+E13 -> 3890 | G13: =F13/C13 -> 1296.6667 | H13: 3900 | I13: 3 | J13: =H13/I13 -> 1300 | K13: =(J13-G13)*I13 -> 10 | L13: =K13*100/F13 -> 0.25706941
